README.md
setup.cfg
setup.py
levne/__init__.py
levne.egg-info/PKG-INFO
levne.egg-info/SOURCES.txt
levne.egg-info/dependency_links.txt
levne.egg-info/requires.txt
levne.egg-info/top_level.txt