Metadata-Version: 1.2
Name: levne
Version: 0.0.1
Summary: A python package for Amino Acid Clustering. Published February 2020
Home-page: https://github.com/Christian-Sidak/levne.git
Author: Christian Šidák
License: UNKNOWN
Platform: UNKNOWN
Classifier: Programming Language :: Python :: 3
Classifier: License :: OSI Approved :: MIT License
Classifier: Operating System :: OS Independent
Requires-Python: >=3.6
